openpylivoxv2/__init__.py
openpylivoxv2/openpylivoxv2.py
openpylivoxv2-1.0.2.dist-info/licenses/LICENSE
openpylivoxv2-1.0.2.dist-info/METADATA
openpylivoxv2-1.0.2.dist-info/WHEEL
openpylivoxv2-1.0.2.dist-info/top_level.txt
openpylivoxv2-1.0.2.dist-info/RECORD
